sentencing/__init__.py
sentencing/example.py
sentencing-0.2.dist-info/METADATA
sentencing-0.2.dist-info/WHEEL
sentencing-0.2.dist-info/top_level.txt
sentencing-0.2.dist-info/RECORD
