Metadata-Version: 2.1
Name: sentencing
Version: 0.2
Summary: test wheel
